{"6c8db041130fc26b95bf45f47aa7bdd5":{"statistic":{"failed":0,"broken":1,"skipped":0,"passed":0,"unknown":0,"total":1},"items":[{"uid":"3fe6737a3ac4b6e9","status":"broken","statusDetails":"Cannot invoke \"ui.locators.LoginPage.getText(String)\" because \"this.loginPage\" is null","time":{"start":1761789641847,"stop":1761789641848,"duration":1}}]},"96ce0c89bf708b9271ecb3f9a393b3fe":{"statistic":{"failed":0,"broken":1,"skipped":0,"passed":0,"unknown":0,"total":1},"items":[{"uid":"5c6c9d53d93318de","status":"broken","statusDetails":"Cannot invoke \"ui.locators.LoginPage.getText(String)\" because \"this.loginPage\" is null","time":{"start":1761789641694,"stop":1761789641712,"duration":18}}]},"f32c723a32d9f68bc9c545519b83350f":{"statistic":{"failed":0,"broken":1,"skipped":0,"passed":0,"unknown":0,"total":1},"items":[{"uid":"e24c39c68c496160","status":"broken","statusDetails":"Cannot invoke \"ui.locators.LoginPage.getText(String)\" because \"this.loginPage\" is null","time":{"start":1761789641842,"stop":1761789641843,"duration":1}}]},"f123fb72f122444bcc41cf004b2f7b7c":{"statistic":{"failed":0,"broken":1,"skipped":0,"passed":0,"unknown":0,"total":1},"items":[{"uid":"f2915d2e12a05df0","status":"broken","statusDetails":"Cannot invoke \"ui.locators.LoginPage.getText(String)\" because \"this.loginPage\" is null","time":{"start":1761789641836,"stop":1761789641837,"duration":1}}]},"adea10a8cbded81c4db449a619fc07b0":{"statistic":{"failed":0,"broken":1,"skipped":0,"passed":0,"unknown":0,"total":1},"items":[{"uid":"a04da99a74a91628","status":"broken","statusDetails":"Cannot invoke \"ui.locators.LoginPage.getText(String)\" because \"this.loginPage\" is null","time":{"start":1761789641830,"stop":1761789641831,"duration":1}}]},"7d2b05525ef124b5e5db990a3af3b2e7":{"statistic":{"failed":0,"broken":1,"skipped":0,"passed":0,"unknown":0,"total":1},"items":[{"uid":"2504b79dc91525d","status":"broken","statusDetails":"Cannot invoke \"ui.locators.LoginPage.getText(String)\" because \"this.loginPage\" is null","time":{"start":1761789641853,"stop":1761789641854,"duration":1}}]}}